apflow/__init__.py
apflow/logger.py
apflow/py.typed
apflow/api/__init__.py
apflow/api/app.py
apflow/api/main.py
apflow/api/protocols.py
apflow/api/a2a/__init__.py
apflow/api/a2a/agent_executor.py
apflow/api/a2a/custom_starlette_app.py
apflow/api/a2a/event_queue_bridge.py
apflow/api/a2a/server.py
apflow/api/a2a/task_routes_adapter.py
apflow/api/docs/__init__.py
apflow/api/docs/openapi.py
apflow/api/docs/swagger_ui.py
apflow/api/mcp/__init__.py
apflow/api/mcp/adapter.py
apflow/api/mcp/resources.py
apflow/api/mcp/server.py
apflow/api/mcp/tools.py
apflow/api/mcp/transport_http.py
apflow/api/mcp/transport_stdio.py
apflow/api/middleware/__init__.py
apflow/api/middleware/db_session.py
apflow/api/routes/__init__.py
apflow/api/routes/base.py
apflow/api/routes/docs.py
apflow/api/routes/system.py
apflow/api/routes/tasks.py
apflow/cli/__init__.py
apflow/cli/api_client.py
apflow/cli/api_gateway_helper.py
apflow/cli/cli_config.py
apflow/cli/decorators.py
apflow/cli/extension.py
apflow/cli/jwt_token.py
apflow/cli/main.py
apflow/cli/commands/__init__.py
apflow/cli/commands/config.py
apflow/cli/commands/daemon.py
apflow/cli/commands/executors.py
apflow/cli/commands/generate.py
apflow/cli/commands/run.py
apflow/cli/commands/serve.py
apflow/cli/commands/tasks.py
apflow/core/__init__.py
apflow/core/builders.py
apflow/core/config_manager.py
apflow/core/decorators.py
apflow/core/types.py
apflow/core/base/__init__.py
apflow/core/base/base_task.py
apflow/core/config/__init__.py
apflow/core/config/registry.py
apflow/core/execution/__init__.py
apflow/core/execution/errors.py
apflow/core/execution/executor_registry.py
apflow/core/execution/streaming_callbacks.py
apflow/core/execution/task_creator.py
apflow/core/execution/task_executor.py
apflow/core/execution/task_manager.py
apflow/core/execution/task_tracker.py
apflow/core/extensions/__init__.py
apflow/core/extensions/base.py
apflow/core/extensions/decorators.py
apflow/core/extensions/executor_metadata.py
apflow/core/extensions/hook.py
apflow-0.13.0.dist-info/licenses/LICENSE
apflow-0.13.0.dist-info/METADATA
apflow-0.13.0.dist-info/WHEEL
apflow-0.13.0.dist-info/entry_points.txt
apflow-0.13.0.dist-info/top_level.txt
apflow-0.13.0.dist-info/RECORD
