Metadata-Version: 2.4
Name: apflow
Version: 0.13.0
Summary: Agent workflow orchestration and execution platform
Author-email: aipartnerup <tercel.yi@gmail.com>
License: Apache-2.0
Project-URL: Homepage, https://aipartnerup.com
Project-URL: Source, https://github.com/aipartnerup/apflow
Keywords: ai,agent,orchestration,workflow,task,crewai,a2a
Classifier: Development Status :: 4 - Beta
Classifier: Intended Audience :: Developers
Classifier: License :: OSI Approved :: Apache Software License
Classifier: Programming Language :: Python :: 3
Classifier: Programming Language :: Python :: 3.10
Classifier: Programming Language :: Python :: 3.11
Classifier: Programming Language :: Python :: 3.12
Requires-Python: >=3.10
License-File: LICENSE
Requires-Dist: pydantic[email]>=2.0.0
Requires-Dist: pydantic-settings>=2.0.0
Requires-Dist: sqlalchemy>=2.0.0
Requires-Dist: sqlalchemy-session-proxy>=0.1.0
Requires-Dist: alembic>=1.13.0
Requires-Dist: duckdb-engine>=0.10.0
Requires-Dist: pytz>=2024.1
Provides-Extra: a2a
Requires-Dist: fastapi>=0.115.0; extra == "a2a"
Requires-Dist: uvicorn[standard]>=0.29.0; extra == "a2a"
Requires-Dist: a2a-sdk[http-server]>=0.3.0; extra == "a2a"
Requires-Dist: httpx[socks]>=0.27.0; extra == "a2a"
Requires-Dist: aiohttp[speedups]>=3.9.0; extra == "a2a"
Requires-Dist: starlette>=0.27.0; extra == "a2a"
Requires-Dist: websockets>=12.0; extra == "a2a"
Requires-Dist: python-jose[cryptography]>=3.3.0; extra == "a2a"
Provides-Extra: cli
Requires-Dist: click>=8.0.0; extra == "cli"
Requires-Dist: rich>=13.0.0; extra == "cli"
Requires-Dist: typer>=0.9.0; extra == "cli"
Requires-Dist: python-dotenv>=1.0.0; extra == "cli"
Requires-Dist: nest_asyncio>=1.5.0; extra == "cli"
Requires-Dist: httpx>=0.27.0; extra == "cli"
Requires-Dist: PyJWT>=2.8.0; extra == "cli"
Requires-Dist: pyyaml>=6.0.0; extra == "cli"
Provides-Extra: postgres
Requires-Dist: asyncpg>=0.29.0; extra == "postgres"
Requires-Dist: psycopg2-binary>=2.9.9; extra == "postgres"
Provides-Extra: crewai
Requires-Dist: crewai[tools]>=1.7.2; extra == "crewai"
Requires-Dist: litellm>=1.0.0; extra == "crewai"
Requires-Dist: anthropic>=0.34.0; extra == "crewai"
Requires-Dist: aiodns>=3.6.1; extra == "crewai"
Provides-Extra: llm-key-config
Provides-Extra: ssh
Requires-Dist: asyncssh>=2.14.0; extra == "ssh"
Provides-Extra: docker
Requires-Dist: docker>=7.0.0; extra == "docker"
Provides-Extra: grpc
Requires-Dist: grpclib>=0.4.7; extra == "grpc"
Requires-Dist: protobuf>=4.25.0; extra == "grpc"
Provides-Extra: mcp
Provides-Extra: llm
Requires-Dist: litellm>=1.0.0; extra == "llm"
Provides-Extra: tools
Requires-Dist: requests>=2.31.0; extra == "tools"
Requires-Dist: beautifulsoup4>=4.12.0; extra == "tools"
Requires-Dist: trafilatura>=2.0.0; extra == "tools"
Requires-Dist: brotli==1.2.0; extra == "tools"
Requires-Dist: bs4>=0.0.2; extra == "tools"
Provides-Extra: standard
Requires-Dist: apflow[a2a,cli,crewai,llm,tools]; extra == "standard"
Provides-Extra: dev
Requires-Dist: pytest>=7.0.0; extra == "dev"
Requires-Dist: pytest-asyncio>=0.21.0; extra == "dev"
Requires-Dist: pytest-cov>=4.0.0; extra == "dev"
Requires-Dist: pytest-timeout>=2.1.0; extra == "dev"
Requires-Dist: black>=23.0.0; extra == "dev"
Requires-Dist: ruff>=0.1.0; extra == "dev"
Requires-Dist: mypy>=1.5.0; extra == "dev"
Requires-Dist: build>=1.0.0; extra == "dev"
Requires-Dist: twine>=4.0.0; extra == "dev"
Requires-Dist: jsonfinder>=0.4.0; extra == "dev"
Requires-Dist: pre-commit>=3.0.0; extra == "dev"
Provides-Extra: all
Requires-Dist: apflow[a2a,cli,crewai,docker,grpc,llm,llm-key-config,mcp,postgres,ssh,tools]; extra == "all"
Dynamic: license-file
